whichlang/__init__.py
whichlang/check.py
whichlang/train_lang_models.py
whichlang/whichlang.py
whichlang/language-models/Assamese.p
whichlang/language-models/Gujarati.p
whichlang/language-models/Hindi.p
whichlang/language-models/Kannada.p
whichlang/language-models/Malayalam.p
whichlang/language-models/Marathi.p
whichlang/language-models/Oriya.p
whichlang/language-models/Punjabi.p
whichlang/language-models/Tamil.p
whichlang/language-models/Telugu.p
whichlang-0.0.4.data/data/whichlang/language-models/Assamese.p
whichlang-0.0.4.data/data/whichlang/language-models/Gujarati.p
whichlang-0.0.4.data/data/whichlang/language-models/Hindi.p
whichlang-0.0.4.data/data/whichlang/language-models/Kannada.p
whichlang-0.0.4.data/data/whichlang/language-models/Malayalam.p
whichlang-0.0.4.data/data/whichlang/language-models/Marathi.p
whichlang-0.0.4.data/data/whichlang/language-models/Oriya.p
whichlang-0.0.4.data/data/whichlang/language-models/Punjabi.p
whichlang-0.0.4.data/data/whichlang/language-models/Tamil.p
whichlang-0.0.4.data/data/whichlang/language-models/Telugu.p
whichlang-0.0.4.dist-info/LICENSE
whichlang-0.0.4.dist-info/METADATA
whichlang-0.0.4.dist-info/WHEEL
whichlang-0.0.4.dist-info/top_level.txt
whichlang-0.0.4.dist-info/RECORD
