Metadata-Version: 2.1
Name: whichlang
Version: 0.0.4
Summary: Does language identification for Indian languages
Home-page: https://github.com/xtraspeed/whichlang
Author: Ashish 
Author-email: <ashish.xtraspeed@gmail.com>
License: UNKNOWN
Keywords: python,language identification
Platform: UNKNOWN
Classifier: Development Status :: 1 - Planning
Classifier: Intended Audience :: Developers
Classifier: License :: OSI Approved :: MIT License
Classifier: Programming Language :: Python :: 3
Classifier: Operating System :: Unix
Classifier: Operating System :: MacOS :: MacOS X
Classifier: Operating System :: Microsoft :: Windows
License-File: LICENSE
